morningstar_ui/__init__.py
morningstar_utilities/__init__.py
morningstar_utils/__init__.py
morningstar_widgets/__init__.py
morningstar_utilities-0.0.1.dist-info/METADATA
morningstar_utilities-0.0.1.dist-info/WHEEL
morningstar_utilities-0.0.1.dist-info/top_level.txt
morningstar_utilities-0.0.1.dist-info/RECORD
